interact/__init__.py
interact/_client.py
interact/_enums.py
interact/_models.py
interact/_test.ipynb
interact/_utils/_logs.py
invoke_interactor-0.1.3.dist-info/LICENSE
invoke_interactor-0.1.3.dist-info/METADATA
invoke_interactor-0.1.3.dist-info/WHEEL
invoke_interactor-0.1.3.dist-info/RECORD
